[
  {
    "id": "152",
    "name": {
      "jp": "チコリータ",
      "en": "chikorita"
    }
  },
  {
    "id": "153",
    "name": {
      "jp": "ベイリーフ",
      "en": "bayleef"
    }
  },
  {
    "id": "154",
    "name": {
      "jp": "メガニウム",
      "en": "meganium"
    }
  },
  {
    "id": "155",
    "name": {
      "jp": "ヒノアラシ",
      "en": "cyndaquil"
    }
  },
  {
    "id": "156",
    "name": {
      "jp": "マグマラシ",
      "en": "quilava"
    }
  },
  {
    "id": "157",
    "name": {
      "jp": "バクフーン",
      "en": "typhlosion"
    }
  },
  {
    "id": "158",
    "name": {
      "jp": "ワニノコ",
      "en": "totodile"
    }
  },
  {
    "id": "159",
    "name": {
      "jp": "アリゲイツ",
      "en": "croconaw"
    }
  },
  {
    "id": "160",
    "name": {
      "jp": "オーダイル",
      "en": "feraligatr"
    }
  },
  {
    "id": "161",
    "name": {
      "jp": "オタチ",
      "en": "sentret"
    }
  },
  {
    "id": "162",
    "name": {
      "jp": "オオタチ",
      "en": "furret"
    }
  },
  {
    "id": "163",
    "name": {
      "jp": "ホーホー",
      "en": "hoothoot"
    }
  },
  {
    "id": "164",
    "name": {
      "jp": "ヨルノズク",
      "en": "noctowl"
    }
  },
  {
    "id": "165",
    "name": {
      "jp": "レディバ",
      "en": "ledyba"
    }
  },
  {
    "id": "166",
    "name": {
      "jp": "レディアン",
      "en": "ledian"
    }
  },
  {
    "id": "167",
    "name": {
      "jp": "イトマル",
      "en": "spinarak"
    }
  },
  {
    "id": "168",
    "name": {
      "jp": "アリアドス",
      "en": "ariados"
    }
  },
  {
    "id": "169",
    "name": {
      "jp": "クロバット",
      "en": "crobat"
    }
  },
  {
    "id": "170",
    "name": {
      "jp": "チョンチー",
      "en": "chinchou"
    }
  },
  {
    "id": "171",
    "name": {
      "jp": "ランターン",
      "en": "lanturn"
    }
  },
  {
    "id": "172",
    "name": {
      "jp": "ピチュー",
      "en": "pichu"
    }
  },
  {
    "id": "173",
    "name": {
      "jp": "ピィ",
      "en": "cleffa"
    }
  },
  {
    "id": "174",
    "name": {
      "jp": "ププリン",
      "en": "igglybuff"
    }
  },
  {
    "id": "175",
    "name": {
      "jp": "トゲピー",
      "en": "togepi"
    }
  },
  {
    "id": "176",
    "name": {
      "jp": "トゲチック",
      "en": "togetic"
    }
  },
  {
    "id": "177",
    "name": {
      "jp": "ネイティ",
      "en": "natu"
    }
  },
  {
    "id": "178",
    "name": {
      "jp": "ネイティオ",
      "en": "xatu"
    }
  },
  {
    "id": "179",
    "name": {
      "jp": "メリープ",
      "en": "mareep"
    }
  },
  {
    "id": "180",
    "name": {
      "jp": "モココ",
      "en": "flaaffy"
    }
  },
  {
    "id": "181",
    "name": {
      "jp": "デンリュウ",
      "en": "ampharos"
    }
  },
  {
    "id": "182",
    "name": {
      "jp": "キレイハナ",
      "en": "bellossom"
    }
  },
  {
    "id": "183",
    "name": {
      "jp": "マリル",
      "en": "marill"
    }
  },
  {
    "id": "184",
    "name": {
      "jp": "マリルリ",
      "en": "azumarill"
    }
  },
  {
    "id": "185",
    "name": {
      "jp": "ウソッキー",
      "en": "sudowoodo"
    }
  },
  {
    "id": "186",
    "name": {
      "jp": "ニョロトノ",
      "en": "politoed"
    }
  },
  {
    "id": "187",
    "name": {
      "jp": "ハネッコ",
      "en": "hoppip"
    }
  },
  {
    "id": "188",
    "name": {
      "jp": "ポポッコ",
      "en": "skiploom"
    }
  },
  {
    "id": "189",
    "name": {
      "jp": "ワタッコ",
      "en": "jumpluff"
    }
  },
  {
    "id": "190",
    "name": {
      "jp": "エイパム",
      "en": "aipom"
    }
  },
  {
    "id": "191",
    "name": {
      "jp": "ヒマナッツ",
      "en": "sunkern"
    }
  },
  {
    "id": "192",
    "name": {
      "jp": "キマワリ",
      "en": "sunflora"
    }
  },
  {
    "id": "193",
    "name": {
      "jp": "ヤンヤンマ",
      "en": "yanma"
    }
  },
  {
    "id": "194",
    "name": {
      "jp": "ウパー",
      "en": "wooper"
    }
  },
  {
    "id": "195",
    "name": {
      "jp": "ヌオー",
      "en": "quagsire"
    }
  },
  {
    "id": "196",
    "name": {
      "jp": "エーフィ",
      "en": "espeon"
    }
  },
  {
    "id": "197",
    "name": {
      "jp": "ブラッキー",
      "en": "umbreon"
    }
  },
  {
    "id": "198",
    "name": {
      "jp": "ヤミカラス",
      "en": "murkow"
    }
  },
  {
    "id": "199",
    "name": {
      "jp": "ヤドキング",
      "en": "slowking"
    }
  },
  {
    "id": "200",
    "name": {
      "jp": "ムウマ",
      "en": "misdreavus"
    }
  },
  {
    "id": "201",
    "name": {
      "jp": "アンノーン",
      "en": "unown"
    }
  },
  {
    "id": "202",
    "name": {
      "jp": "ソーナンス",
      "en": "wobbuffet"
    }
  },
  {
    "id": "203",
    "name": {
      "jp": "キリンリキ",
      "en": "girafarig"
    }
  },
  {
    "id": "204",
    "name": {
      "jp": "クヌギダマ",
      "en": "pineco"
    }
  },
  {
    "id": "205",
    "name": {
      "jp": "フォレトス",
      "en": "forretress"
    }
  },
  {
    "id": "206",
    "name": {
      "jp": "ノコッチ",
      "en": "dunsparce"
    }
  },
  {
    "id": "207",
    "name": {
      "jp": "グライガー",
      "en": "gligar"
    }
  },
  {
    "id": "208",
    "name": {
      "jp": "ハガネール",
      "en": "steelix"
    }
  },
  {
    "id": "209",
    "name": {
      "jp": "ブルー",
      "en": "snubbull"
    }
  },
  {
    "id": "210",
    "name": {
      "jp": "グランブル",
      "en": "granbull"
    }
  },
  {
    "id": "211",
    "name": {
      "jp": "ハリーセン",
      "en": "qwilfish"
    }
  },
  {
    "id": "212",
    "name": {
      "jp": "ハッサム",
      "en": "scizor"
    }
  },
  {
    "id": "213",
    "name": {
      "jp": "ツボツボ",
      "en": "shuckle"
    }
  },
  {
    "id": "214",
    "name": {
      "jp": "ヘラクロス",
      "en": "heracross"
    }
  },
  {
    "id": "215",
    "name": {
      "jp": "ニューラ",
      "en": "sneasel"
    }
  },
  {
    "id": "216",
    "name": {
      "jp": "ヒメグマ",
      "en": "teddiursa"
    }
  },
  {
    "id": "217",
    "name": {
      "jp": "リングマ",
      "en": "ursaring"
    }
  },
  {
    "id": "218",
    "name": {
      "jp": "マグマッグ",
      "en": "slugma"
    }
  },
  {
    "id": "219",
    "name": {
      "jp": "マグカルゴ",
      "en": "magcargo"
    }
  },
  {
    "id": "220",
    "name": {
      "jp": "ウリムー",
      "en": "swinub"
    }
  },
  {
    "id": "221",
    "name": {
      "jp": "イノムー",
      "en": "piloswine"
    }
  },
  {
    "id": "222",
    "name": {
      "jp": "サニーゴ",
      "en": "corsola"
    }
  },
  {
    "id": "223",
    "name": {
      "jp": "テッポウオ",
      "en": "remoraid"
    }
  },
  {
    "id": "224",
    "name": {
      "jp": "オクタン",
      "en": "octillery"
    }
  },
  {
    "id": "225",
    "name": {
      "jp": "デリバード",
      "en": "delibird"
    }
  },
  {
    "id": "226",
    "name": {
      "jp": "マンタイン",
      "en": "mantine"
    }
  },
  {
    "id": "227",
    "name": {
      "jp": "エアームド",
      "en": "skarmory"
    }
  },
  {
    "id": "228",
    "name": {
      "jp": "デルビル",
      "en": "houndour"
    }
  },
  {
    "id": "229",
    "name": {
      "jp": "ヘルガー",
      "en": "houndoom"
    }
  },
  {
    "id": "230",
    "name": {
      "jp": "キングドラ",
      "en": "kingdra"
    }
  },
  {
    "id": "231",
    "name": {
      "jp": "ゴマゾウ",
      "en": "phanpy"
    }
  },
  {
    "id": "232",
    "name": {
      "jp": "ドンファン",
      "en": "donphan"
    }
  },
  {
    "id": "233",
    "name": {
      "jp": "ポリゴン2",
      "en": "porygon2"
    }
  },
  {
    "id": "234",
    "name": {
      "jp": "オドシシ",
      "en": "stantler"
    }
  },
  {
    "id": "235",
    "name": {
      "jp": "ドーブル",
      "en": "smeargle"
    }
  },
  {
    "id": "236",
    "name": {
      "jp": "バルキー",
      "en": "tyrogue"
    }
  },
  {
    "id": "237",
    "name": {
      "jp": "カポエラー",
      "en": "hitmontop"
    }
  },
  {
    "id": "238",
    "name": {
      "jp": "ムチュール",
      "en": "smoochum"
    }
  },
  {
    "id": "239",
    "name": {
      "jp": "エレキッド",
      "en": "elekid"
    }
  },
  {
    "id": "240",
    "name": {
      "jp": "ブビィ",
      "en": "magby"
    }
  },
  {
    "id": "241",
    "name": {
      "jp": "ミルタンク",
      "en": "miltank"
    }
  },
  {
    "id": "242",
    "name": {
      "jp": "ハピナス",
      "en": "blissey"
    }
  },
  {
    "id": "243",
    "name": {
      "jp": "ライコウ",
      "en": "raikou"
    }
  },
  {
    "id": "244",
    "name": {
      "jp": "エンテイ",
      "en": "entei"
    }
  },
  {
    "id": "245",
    "name": {
      "jp": "スイクン",
      "en": "suicine"
    }
  },
  {
    "id": "246",
    "name": {
      "jp": "ヨーギラス",
      "en": "larvitar"
    }
  },
  {
    "id": "247",
    "name": {
      "jp": "サナギラス",
      "en": "pupitar"
    }
  },
  {
    "id": "248",
    "name": {
      "jp": "バンギラス",
      "en": "tyranitar"
    }
  },
  {
    "id": "249",
    "name": {
      "jp": "ルギア",
      "en": "lugia"
    }
  },
  {
    "id": "250",
    "name": {
      "jp": "ホウオウ",
      "en": "ho-oh"
    }
  },
  {
    "id": "251",
    "name": {
      "jp": "セレビィ",
      "en": "Celebi"
    }
  }
]
